weiboo/__init__.py
weiboo-0.0.18.dist-info/LICENSE
weiboo-0.0.18.dist-info/METADATA
weiboo-0.0.18.dist-info/WHEEL
weiboo-0.0.18.dist-info/top_level.txt
weiboo-0.0.18.dist-info/RECORD
